odoo/addons/cmis/README.rst
odoo/addons/cmis/__init__.py
odoo/addons/cmis/__manifest__.py
odoo/addons/cmis/exceptions.py
odoo/addons/cmis/demo/cmis_backend_demo.xml
odoo/addons/cmis/i18n/cmis.pot
odoo/addons/cmis/i18n/de.po
odoo/addons/cmis/i18n/fr.po
odoo/addons/cmis/models/__init__.py
odoo/addons/cmis/models/cmis_backend.py
odoo/addons/cmis/readme/CONTRIBUTORS.rst
odoo/addons/cmis/readme/DESCRIPTION.rst
odoo/addons/cmis/readme/HISTORY.rst
odoo/addons/cmis/readme/INSTALL.rst
odoo/addons/cmis/security/cmis_backend.xml
odoo/addons/cmis/static/description/icon.png
odoo/addons/cmis/static/description/index.html
odoo/addons/cmis/tests/__init__.py
odoo/addons/cmis/tests/test_cmis_backend.py
odoo/addons/cmis/views/cmis_backend.xml
odoo14_addon_cmis-14.0.1.0.1.dist-info/METADATA
odoo14_addon_cmis-14.0.1.0.1.dist-info/WHEEL
odoo14_addon_cmis-14.0.1.0.1.dist-info/top_level.txt
odoo14_addon_cmis-14.0.1.0.1.dist-info/RECORD
