Metadata-Version: 2.1
Name: odoo14-addon-cmis
Version: 14.0.1.0.1
Summary: Connect Odoo with a CMIS server
Home-page: https://github.com/OCA/connector-cmis
Author: Savoir-faire Linux, ACSONE SA/NV, Odoo Community Association (OCA)
Author-email: support@odoo-community.org
License: AGPL-3
Platform: UNKNOWN
Classifier: Programming Language :: Python
Classifier: Framework :: Odoo
Classifier: Framework :: Odoo :: 14.0
Classifier: License :: OSI Approved :: GNU Affero General Public License v3
Classifier: Development Status :: 6 - Mature
Requires-Python: >=3.6
Requires-Dist: cmislib
Requires-Dist: odoo (<14.1dev,>=14.0a)
